osprey/__init__.py
osprey/config.py
osprey/cross_validators.py
osprey/dataset_loaders.py
osprey/entry_point.py
osprey/eval_scopes.py
osprey/execute_currentbest.py
osprey/execute_dump.py
osprey/execute_plot.py
osprey/execute_skeleton.py
osprey/execute_worker.py
osprey/fit_estimator.py
osprey/plot.py
osprey/search_space.py
osprey/strategies.py
osprey/subclass_factory.py
osprey/trials.py
osprey/utils.py
osprey/version.py
osprey/cli/__init__.py
osprey/cli/main.py
osprey/cli/parser_currentbest.py
osprey/cli/parser_dump.py
osprey/cli/parser_plot.py
osprey/cli/parser_skeleton.py
osprey/cli/parser_worker.py
osprey/data/MANIFEST
osprey/data/default_config.yaml
osprey/data/msmbuilder_skeleton_config.yaml
osprey/data/sklearn_skeleton_config.yaml
osprey/plugins/__init__.py
osprey/plugins/plugin_pylearn2.py
osprey/plugins/tests/__init__.py
osprey/plugins/tests/test_plugin_pylearn2.py
osprey/tests/__init__.py
osprey/tests/test_cli_skeleton.py
osprey/tests/test_cli_worker_and_dump.py
osprey/tests/test_config.py
osprey/tests/test_dataset_loader.py
osprey/tests/test_entry_point.py
osprey/tests/test_fit_estimator.py
osprey/tests/test_search_space.py
osprey/tests/test_strategies.py
osprey/tests/test_trials.py
osprey/tests/test_utils.py
osprey-1.0.0.dist-info/DESCRIPTION.rst
osprey-1.0.0.dist-info/METADATA
osprey-1.0.0.dist-info/RECORD
osprey-1.0.0.dist-info/WHEEL
osprey-1.0.0.dist-info/entry_points.txt
osprey-1.0.0.dist-info/metadata.json
osprey-1.0.0.dist-info/top_level.txt
