Metadata-Version: 1.1
Name: osprey
Version: 1.0.0
Summary: |Build Status| |Coverage Status| |PyPi version| [|License|\ ]
Home-page: https://github.com/msmbuilder/osprey
Author: Robert T. McGibbon
Author-email: rmcgibbo@gmail.com
License: Apache Software License
Download-URL: https://pypi.python.org/pypi/osprey/
Platform: Windows
Platform: Linux
Platform: Mac OS-X
Platform: Unix
Classifier: Development Status :: 3 - Alpha
Classifier: Intended Audience :: Science/Research
Classifier: License :: OSI Approved :: Apache Software License
Classifier: Programming Language :: Python
Classifier: Programming Language :: Python :: 2.7
Classifier: Programming Language :: Python :: 3
Classifier: Programming Language :: Python :: 3.4
Classifier: Programming Language :: Python :: 3.5
Classifier: Operating System :: Unix
Classifier: Operating System :: MacOS
Classifier: Operating System :: Microsoft :: Windows
Classifier: Topic :: Scientific/Engineering
Classifier: Topic :: Scientific/Engineering :: Information Analysis
